dmr/__init__.py
dmr/converter.py
dmr/dmr.py
dmr/models/__init__.py
dmr/models/body_type.py
dmr/models/insurance.py
dmr/models/propulsion_type.py
dmr/models/use_type.py
dmr/models/vehicle.py
dmr/models/vehicle_type.py
dmr/utils/__init__.py
dmr/utils/async_scraper.py
dmr/utils/errors.py
dmr/utils/extract_data.py
dmr/utils/headers.py
dmr/utils/scraper.py
dmr/utils/user_agent.py
dmr/utils/xpaths.py
dmr.py-1.1.3.dist-info/LICENSE
dmr.py-1.1.3.dist-info/METADATA
dmr.py-1.1.3.dist-info/WHEEL
dmr.py-1.1.3.dist-info/top_level.txt
dmr.py-1.1.3.dist-info/RECORD
