Metadata-Version: 2.1
Name: dmr.py
Version: 1.1.3
Summary: Pull data directly from the danish vehicle register with dmr.py
Author-email: Jasper <jasper@jazper.dk>
License: MIT License
Project-URL: Homepage, https://github.com/j4asper/dmr.py
Project-URL: Bug Tracker, https://github.com/j4asper/dmr.py/issues
Classifier: License :: OSI Approved :: MIT License
Classifier: Intended Audience :: Developers
Classifier: Natural Language :: English
Classifier: Operating System :: OS Independent
Classifier: Programming Language :: Python :: 3.8
Classifier: Programming Language :: Python :: 3.9
Classifier: Programming Language :: Python :: 3.10
Classifier: Programming Language :: Python :: 3.11
Classifier: Programming Language :: Python :: 3.12
Classifier: Topic :: Internet
Classifier: Topic :: Software Development :: Libraries
Classifier: Topic :: Software Development :: Libraries :: Python Modules
Classifier: Topic :: Utilities
Requires-Python: >=3.8
License-File: LICENSE
Requires-Dist: lxml ==5.2.2
Requires-Dist: requests ==2.32.3
Requires-Dist: aiohttp ==3.9.5
Requires-Dist: pydantic ==2.7.4
Provides-Extra: speed
Requires-Dist: aiodns >=3.1.1 ; extra == 'speed'
Requires-Dist: Brotli ; extra == 'speed'
Requires-Dist: cchardet ; extra == 'speed'
Provides-Extra: test
Requires-Dist: pytest ==7.4.3 ; extra == 'test'
